smartscanner/__init__.py
smartscanner/scanner.py
smartscanner-0.1.0.dist-info/METADATA
smartscanner-0.1.0.dist-info/WHEEL
smartscanner-0.1.0.dist-info/top_level.txt
smartscanner-0.1.0.dist-info/RECORD
