Metadata-Version: 2.4
Name: smartscanner
Version: 0.1.0
Summary: Document scanning pipeline: detect, warp, deskew, enhance, export to PDF.
Author: Abhinav Prasad
Requires-Python: >=3.8
Requires-Dist: opencv-python
Requires-Dist: numpy
Requires-Dist: imutils
Requires-Dist: Pillow
Dynamic: author
Dynamic: requires-dist
Dynamic: requires-python
Dynamic: summary
